README.md
setup.py
dsnd_distributions_lnsd/Binomialdistribution.py
dsnd_distributions_lnsd/Gaussiandistribution.py
dsnd_distributions_lnsd/Generaldistribution.py
dsnd_distributions_lnsd/__init__.py
dsnd_distributions_lnsd.egg-info/PKG-INFO
dsnd_distributions_lnsd.egg-info/SOURCES.txt
dsnd_distributions_lnsd.egg-info/dependency_links.txt
dsnd_distributions_lnsd.egg-info/not-zip-safe
dsnd_distributions_lnsd.egg-info/top_level.txt