Metadata-Version: 1.0
Name: dsnd-distributions-lnsd
Version: 0.2
Summary: Gaussian and Binomial distributions
Home-page: UNKNOWN
Author: Lucas Dantas
Author-email: lucasnsdantas@gmail.com
License: UNKNOWN
Platform: UNKNOWN
